directory_api_external/__init__.py
directory_api_external/client.py
directory_api_external/dummy_client.py
directory_api_external/supplier.py
directory_api_external/version.py
directory_api_external-5.0.0.dist-info/LICENSE
directory_api_external-5.0.0.dist-info/METADATA
directory_api_external-5.0.0.dist-info/WHEEL
directory_api_external-5.0.0.dist-info/top_level.txt
directory_api_external-5.0.0.dist-info/RECORD
