Metadata-Version: 2.1
Name: directory-api-external
Version: 5.0.0
Summary: Python API client for Export Directory.
Home-page: https://github.com/uktrade/directory-api-client
Author: Department for International Trade
License: MIT
Platform: UNKNOWN
Classifier: Development Status :: 5 - Production/Stable
Classifier: Environment :: Web Environment
Classifier: Framework :: Django
Classifier: Framework :: Django :: 1.11
Classifier: Intended Audience :: Developers
Classifier: License :: OSI Approved :: MIT License
Classifier: Natural Language :: English
Classifier: Operating System :: OS Independent
Classifier: Programming Language :: Python :: 3.5
Classifier: Topic :: Software Development :: Libraries :: Python Modules
Requires-Dist: directory-client-core (<5.0.0,>=4.0.2)
